{
  "version": "7",
  "dialect": "postgresql",
  "entries": [
    {
      "idx": 0,
      "version": "7",
      "when": 1775853047351,
      "tag": "0000_cooing_chronomancer",
      "breakpoints": true
    },
    {
      "idx": 1,
      "version": "7",
      "when": 1775870540861,
      "tag": "0001_shallow_snowbird",
      "breakpoints": true
    },
    {
      "idx": 2,
      "version": "7",
      "when": 1775914657583,
      "tag": "0002_black_gabe_jones",
      "breakpoints": true
    }
  ]
}